betula/__init__.py
betula/betula.py
betula/version.py
betula-0.1.0.dist-info/METADATA
betula-0.1.0.dist-info/WHEEL
betula-0.1.0.dist-info/top_level.txt
betula-0.1.0.dist-info/RECORD
