Metadata-Version: 2.1
Name: betula
Version: 0.1.0
Summary: Optofluidic cell assay data analysis
Home-page: UNKNOWN
Author: Peter Vegh
License: UNKNOWN
Keywords: biology
Platform: UNKNOWN
